guerilla_transform_stack/__init__.py
guerilla_transform_stack/test.py
guerilla_transform_stack/transform.py
guerilla_transform_stack/transform_stack.py
guerilla_transform_stack-0.0.1.dist-info/LICENSE
guerilla_transform_stack-0.0.1.dist-info/METADATA
guerilla_transform_stack-0.0.1.dist-info/WHEEL
guerilla_transform_stack-0.0.1.dist-info/top_level.txt
guerilla_transform_stack-0.0.1.dist-info/RECORD
