Metadata-Version: 2.1
Name: guerilla-transform-stack
Version: 0.0.1
Summary: Manipulate Guerilla transform stack as Python object.
Home-page: https://github.com/Narann/guerilla-transform-stack
Author: Dorian Fevrier
Author-email: fevrier.dorian@yahoo.fr
License: MIT
Keywords: guerilla,transform,stack
Platform: UNKNOWN
Classifier: Development Status :: 3 - Alpha
Classifier: License :: OSI Approved :: MIT License
Classifier: Programming Language :: Python :: 2.7
Classifier: Operating System :: OS Independent
Requires-Python: >=2.7
